timos_tools/__init__.py
timos_tools/version.py
timos_tools/json/__init__.py
timos_tools/json/handle.py
timos_tools-0.0.4.dist-info/METADATA
timos_tools-0.0.4.dist-info/WHEEL
timos_tools-0.0.4.dist-info/top_level.txt
timos_tools-0.0.4.dist-info/RECORD
